qflash_auth_jwt_package/__init__.py
qflash_auth_jwt_package/authenticated_route.py
qflash_auth_jwt_package/jwt.py
qflash_auth_jwt_package-1.2.2.dist-info/LICENSE
qflash_auth_jwt_package-1.2.2.dist-info/METADATA
qflash_auth_jwt_package-1.2.2.dist-info/WHEEL
qflash_auth_jwt_package-1.2.2.dist-info/top_level.txt
qflash_auth_jwt_package-1.2.2.dist-info/RECORD
