Metadata-Version: 2.1
Name: qflash_auth_jwt_package
Version: 1.2.2
Summary: a small package for implement jwt security in API
Home-page: https://github.com/Quasar-Flash
Author: Marlon Martins
Author-email: marlon.martins@qflash.com.br
License: MIT License
Keywords: Package
License-File: LICENSE
Requires-Dist: pyjwt<3.0.0,>=2.8.0
